gllm/__init__.py
gllm/cli.py
gllm/core.py
gllm_cli-0.3.1.dist-info/METADATA
gllm_cli-0.3.1.dist-info/WHEEL
gllm_cli-0.3.1.dist-info/entry_points.txt
gllm_cli-0.3.1.dist-info/licenses/LICENSE
gllm_cli-0.3.1.dist-info/RECORD
