Metadata-Version: 2.4
Name: gllm-cli
Version: 0.3.1
Summary: Generate Terminal Commands from Natural Language with Gemini
Project-URL: License, https://opensource.org/licenses/MIT
Project-URL: repository, https://github.com/hoishing/gllm
License: MIT
License-File: LICENSE
Requires-Python: >=3.12
Requires-Dist: click
Requires-Dist: google-genai
